Workbook

Sheet Cómo revisar
A1: Revisión de textos · Acreditaciones de arbolado urbano
A2: Inventario generado de la versión de prueba 0.67 · 812 textos
A4: Cómo revisar
A5: 1. Ve a la hoja «Textos». Filtra por Pantalla, Tipo o Quién lo ve para revisar por partes (por ejemplo, primero todos los avisos).
A6: 2. «Cuándo aparece» dice en qué caso ve la persona ese texto (perfil, estado de la solicitud, respuesta o error).
A7: 3. Si el texto está bien, cambia Estado a «OK». Si no, escribe el texto nuevo en «Tu corrección» y pon «Cambiar».
A8: 4. «Quitar» elimina el texto; «Duda» deja una pregunta en «Comentario».
A9: 5. Sólo edita las columnas amarillas (Tu corrección, Estado, Comentario). Las demás vienen del sistema.
A10: 6. «Observación de Claude» señala textos que contradicen una regla o tienen un pendiente.
A11: 7. Devuélveme el archivo: aplico los cambios en el sitio, el catálogo de la base y los mensajes, corro las pruebas y publico la siguiente versión.
A13: Ejemplo de fila revisada
A14: Texto actual | B14: Llenas tu solicitud y cargas tus documentos en PDF o en foto.
A15: Tu corrección | B15: Llenas tu solicitud y cargas tus documentos en PDF.
A16: Estado | B16: Cambiar
A17: Comentario | B17: Sólo se aceptan PDF.
A19: Avance por pantalla
A20: Pantalla | B20: Textos | C20: Pendientes | D20: OK | E20: Cambiar | F20: Quitar o duda
A21: Todas las pantallas | B21: =COUNTIF(Textos!$B$2:$B$813,A21) | C21: =COUNTIFS(Textos!$B$2:$B$813,A21,Textos!$H$2:$H$813,"Pendiente") | D21: =COUNTIFS(Textos!$B$2:$B$813,A21,Textos!$H$2:$H$813,"OK") | E21: =COUNTIFS(Textos!$B$2:$B$813,A21,Textos!$H$2:$H$813,"Cambiar") | F21: =COUNTIFS(Textos!$B$2:$B$813,A21,Textos!$H$2:$H$813,"Quitar")+COUNTIFS(Textos!$B$2:$B$813,A21,Textos!$H$2:$H$813,"Duda")
A22: Inicio | B22: =COUNTIF(Textos!$B$2:$B$813,A22) | C22: =COUNTIFS(Textos!$B$2:$B$813,A22,Textos!$H$2:$H$813,"Pendiente") | D22: =COUNTIFS(Textos!$B$2:$B$813,A22,Textos!$H$2:$H$813,"OK") | E22: =COUNTIFS(Textos!$B$2:$B$813,A22,Textos!$H$2:$H$813,"Cambiar") | F22: =COUNTIFS(Textos!$B$2:$B$813,A22,Textos!$H$2:$H$813,"Quitar")+COUNTIFS(Textos!$B$2:$B$813,A22,Textos!$H$2:$H$813,"Duda")
A23: Crea tu cuenta | B23: =COUNTIF(Textos!$B$2:$B$813,A23) | C23: =COUNTIFS(Textos!$B$2:$B$813,A23,Textos!$H$2:$H$813,"Pendiente") | D23: =COUNTIFS(Textos!$B$2:$B$813,A23,Textos!$H$2:$H$813,"OK") | E23: =COUNTIFS(Textos!$B$2:$B$813,A23,Textos!$H$2:$H$813,"Cambiar") | F23: =COUNTIFS(Textos!$B$2:$B$813,A23,Textos!$H$2:$H$813,"Quitar")+COUNTIFS(Textos!$B$2:$B$813,A23,Textos!$H$2:$H$813,"Duda")
A24: Entrar | B24: =COUNTIF(Textos!$B$2:$B$813,A24) | C24: =COUNTIFS(Textos!$B$2:$B$813,A24,Textos!$H$2:$H$813,"Pendiente") | D24: =COUNTIFS(Textos!$B$2:$B$813,A24,Textos!$H$2:$H$813,"OK") | E24: =COUNTIFS(Textos!$B$2:$B$813,A24,Textos!$H$2:$H$813,"Cambiar") | F24: =COUNTIFS(Textos!$B$2:$B$813,A24,Textos!$H$2:$H$813,"Quitar")+COUNTIFS(Textos!$B$2:$B$813,A24,Textos!$H$2:$H$813,"Duda")
A25: Pantallas con cuenta | B25: =COUNTIF(Textos!$B$2:$B$813,A25) | C25: =COUNTIFS(Textos!$B$2:$B$813,A25,Textos!$H$2:$H$813,"Pendiente") | D25: =COUNTIFS(Textos!$B$2:$B$813,A25,Textos!$H$2:$H$813,"OK") | E25: =COUNTIFS(Textos!$B$2:$B$813,A25,Textos!$H$2:$H$813,"Cambiar") | F25: =COUNTIFS(Textos!$B$2:$B$813,A25,Textos!$H$2:$H$813,"Quitar")+COUNTIFS(Textos!$B$2:$B$813,A25,Textos!$H$2:$H$813,"Duda")
A26: Mis trámites | B26: =COUNTIF(Textos!$B$2:$B$813,A26) | C26: =COUNTIFS(Textos!$B$2:$B$813,A26,Textos!$H$2:$H$813,"Pendiente") | D26: =COUNTIFS(Textos!$B$2:$B$813,A26,Textos!$H$2:$H$813,"OK") | E26: =COUNTIFS(Textos!$B$2:$B$813,A26,Textos!$H$2:$H$813,"Cambiar") | F26: =COUNTIFS(Textos!$B$2:$B$813,A26,Textos!$H$2:$H$813,"Quitar")+COUNTIFS(Textos!$B$2:$B$813,A26,Textos!$H$2:$H$813,"Duda")
A27: Solicitud | B27: =COUNTIF(Textos!$B$2:$B$813,A27) | C27: =COUNTIFS(Textos!$B$2:$B$813,A27,Textos!$H$2:$H$813,"Pendiente") | D27: =COUNTIFS(Textos!$B$2:$B$813,A27,Textos!$H$2:$H$813,"OK") | E27: =COUNTIFS(Textos!$B$2:$B$813,A27,Textos!$H$2:$H$813,"Cambiar") | F27: =COUNTIFS(Textos!$B$2:$B$813,A27,Textos!$H$2:$H$813,"Quitar")+COUNTIFS(Textos!$B$2:$B$813,A27,Textos!$H$2:$H$813,"Duda")
A28: Mis datos | B28: =COUNTIF(Textos!$B$2:$B$813,A28) | C28: =COUNTIFS(Textos!$B$2:$B$813,A28,Textos!$H$2:$H$813,"Pendiente") | D28: =COUNTIFS(Textos!$B$2:$B$813,A28,Textos!$H$2:$H$813,"OK") | E28: =COUNTIFS(Textos!$B$2:$B$813,A28,Textos!$H$2:$H$813,"Cambiar") | F28: =COUNTIFS(Textos!$B$2:$B$813,A28,Textos!$H$2:$H$813,"Quitar")+COUNTIFS(Textos!$B$2:$B$813,A28,Textos!$H$2:$H$813,"Duda")
A29: Verificar una acreditación | B29: =COUNTIF(Textos!$B$2:$B$813,A29) | C29: =COUNTIFS(Textos!$B$2:$B$813,A29,Textos!$H$2:$H$813,"Pendiente") | D29: =COUNTIFS(Textos!$B$2:$B$813,A29,Textos!$H$2:$H$813,"OK") | E29: =COUNTIFS(Textos!$B$2:$B$813,A29,Textos!$H$2:$H$813,"Cambiar") | F29: =COUNTIFS(Textos!$B$2:$B$813,A29,Textos!$H$2:$H$813,"Quitar")+COUNTIFS(Textos!$B$2:$B$813,A29,Textos!$H$2:$H$813,"Duda")
A30: Mensajes del formulario (estándar) | B30: =COUNTIF(Textos!$B$2:$B$813,A30) | C30: =COUNTIFS(Textos!$B$2:$B$813,A30,Textos!$H$2:$H$813,"Pendiente") | D30: =COUNTIFS(Textos!$B$2:$B$813,A30,Textos!$H$2:$H$813,"OK") | E30: =COUNTIFS(Textos!$B$2:$B$813,A30,Textos!$H$2:$H$813,"Cambiar") | F30: =COUNTIFS(Textos!$B$2:$B$813,A30,Textos!$H$2:$H$813,"Quitar")+COUNTIFS(Textos!$B$2:$B$813,A30,Textos!$H$2:$H$813,"Duda")
A31: Mensajes al guardar o enviar | B31: =COUNTIF(Textos!$B$2:$B$813,A31) | C31: =COUNTIFS(Textos!$B$2:$B$813,A31,Textos!$H$2:$H$813,"Pendiente") | D31: =COUNTIFS(Textos!$B$2:$B$813,A31,Textos!$H$2:$H$813,"OK") | E31: =COUNTIFS(Textos!$B$2:$B$813,A31,Textos!$H$2:$H$813,"Cambiar") | F31: =COUNTIFS(Textos!$B$2:$B$813,A31,Textos!$H$2:$H$813,"Quitar")+COUNTIFS(Textos!$B$2:$B$813,A31,Textos!$H$2:$H$813,"Duda")
A32: Total | B32: =SUM(B21:B31) | C32: =SUM(C21:C31) | D32: =SUM(D21:D31) | E32: =SUM(E21:E31) | F32: =SUM(F21:F31)

Sheet Textos
A1: ID | B1: Pantalla | C1: Sección | D1: Tipo | E1: Cuándo aparece | F1: Texto actual | G1: Tu corrección | H1: Estado | I1: Comentario | J1: Observación de Claude | K1: Quién lo ve | L1: Dónde se cambia
A2: T001 | B2: Todas las pantallas | C2: Cabecera | D2: Título del sistema | E2: Siempre | F2: Acreditaciones de arbolado urbano | H2: Pendiente | K2: Persona solicitante | L2: Todas las páginas
A3: T002 | B3: Todas las pantallas | C3: Pie | D3: Texto | E3: Siempre | F3: Secretaría del Medio Ambiente de la Ciudad de México · Sistema de Información Ambiental. | H3: Pendiente | K3: Persona solicitante | L3: Todas las páginas
A4: T003 | B4: Todas las pantallas | C4: Acceso con teclado | D4: Enlace | E4: Al navegar con teclado | F4: Ir al contenido | H4: Pendiente | K4: Persona solicitante | L4: Todas las páginas
A5: T004 | B5: Todas las pantallas | C5: Pie | D5: Distintivo | E5: Versión de prueba | F5: Versión de prueba 0.N | H5: Pendiente | K5: Persona solicitante | L5: Código del sitio (sitio/app/version-visible.js)
A6: T005 | B6: Inicio | C6: Acreditación de poda y derribo, y de dictaminador técnico | D6: Título | E6: Siempre | F6: Acreditación de poda y derribo, y de dictaminador técnico | H6: Pendiente | K6: Persona solicitante | L6: Página (sitio/index.html)
A7: T006 | B7: Inicio | C7: Acreditación de poda y derribo, y de dictaminador técnico | D7: Introducción | E7: Siempre | F7: Para trabajar en el arbolado urbano de la Ciudad de México necesitas una acreditación vigente de la Secretaría. Aquí la solicitas por primera vez o la renuevas, y das seguimiento a tu trámite. | H7: Pendiente | K7: Persona solicitante | L7: Página (sitio/index.html)
A8: T007 | B8: Inicio | C8: Acreditación de poda y derribo, y de dictaminador técnico | D8: Texto | E8: Siempre | F8: Crea tu cuenta La primera vez. Necesitas tu CURP y un correo. | H8: Pendiente | K8: Persona solicitante | L8: Página (sitio/index.html)
A9: T008 | B9: Inicio | C9: Acreditación de poda y derribo, y de dictaminador técnico | D9: Texto | E9: Siempre | F9: Entra a tu cuenta Inicia o renueva tu acreditación y consulta en qué va tu trámite. | H9: Pendiente | K9: Persona solicitante | L9: Página (sitio/index.html)
A10: T009 | B10: Inicio | C10: Acreditación de poda y derribo, y de dictaminador técnico | D10: Texto | E10: Siempre | F10: Verifica una acreditación Consulta si una acreditación está vigente. No necesitas cuenta. | H10: Pendiente | K10: Persona solicitante | L10: Página (sitio/index.html)
A11: T010 | B11: Inicio | C11: Acreditación de poda y derribo, y de dictaminador técnico | D11: Texto | E11: Siempre | F11: Material de estudio Los documentos para preparar el examen. No necesitas cuenta. | H11: Pendiente | K11: Persona solicitante | L11: Página (sitio/index.html)
A12: T011 | B12: Inicio | C12: Cómo es el trámite | D12: Título | E12: Siempre | F12: Cómo es el trámite | H12: Pendiente | K12: Persona solicitante | L12: Página (sitio/index.html)
A13: T012 | B13: Inicio | C13: Cómo es el trámite | D13: Texto | E13: Siempre | F13: Creas tu cuenta con tu CURP y una fotografía de frente. Cada persona hace su propio trámite y necesita tener 18 años cumplidos el día de su solicitud. | H13: Pendiente | K13: Persona solicitante | L13: Página (sitio/index.html)
... A25: T024 | B25: Inicio | C25: Requisitos | D25: Texto | E25: Siempre | F25: Los documentos se cargan sólo en PDF, de hasta 5 MB cada uno. Al crear tu cuenta, además, cargas o tomas con tu teléfono una fotografía de frente (JPG o PNG). | H25: Pendiente | K25: Persona solicitante | L25: Página (sitio/index.html)
A26: T025 | B26: Inicio | C26: Requisitos | D26: Texto | E26: Siempre | F26: Cargando requisitos… | H26: Pendiente | J26: Texto momentáneo mientras cargan los datos. | K26: Persona solicitante | L26: Página (sitio/index.html)
A27: T026 | B27: Inicio | C27: Requisitos | D27: Título desplegable | E27: Uno por acreditación y modalidad | F27: «Poda y derribo» o «Dictaminador técnico» · «solicitud nueva» o «renovación» | H27: Pendiente | K27: Persona solicitante | L27: Código del sitio (sitio/app/inicio.js)
A28: T027 | B28: Inicio | C28: Requisitos | D28: Texto | E28: Requisito que se entrega en la cita | F28: Se entrega en la cita de cotejo. | H28: Pendiente | K28: Persona solicitante | L28: Código del sitio (sitio/app/inicio.js)
A29: T028 | B29: Inicio | C29: Requisitos | D29: Texto | E29: Requisito que se hace al entregar la credencial | F29: Se hace al recoger tu credencial. | H29: Pendiente | K29: Persona solicitante | L29: Código del sitio (sitio/app/inicio.js)
A30: T029 | B30: Inicio | C30: Requisitos | D30: Texto | E30: Bajo cada lista de requisitos | F30: Curso de N días; asistencia mínima de M días; calificación mínima del examen: X. Pago de derechos: $… (o «pendiente de la Gaceta Oficial»). | H30: Pendiente | K30: Persona solicitante | L30: Código del sitio (sitio/app/inicio.js)
A31: T030 | B31: Inicio | C31: Requisitos | D31: Error | E31: Si no se pudo cargar el catálogo | F31: No se pudieron cargar los requisitos. Intenta de nuevo más tarde. | H31: Pendiente | K31: Persona solicitante | L31: Código del sitio (sitio/app/inicio.js)
A32: T031 | B32: Crea tu cuenta | C32: — | D32: Botón o enlace | E32: Siempre | F32: Inicio | H32: Pendiente | K32: Persona solicitante | L32: Página (sitio/cuenta.html)
A33: T032 | B33: Crea tu cuenta | C33: — | D33: Aviso | E33: Siempre | F33: Ya entraste a tu cuenta Entraste como . Tu solicitud y su avance están en «Mis trámites». Ir a mis trámites ¿Vas a crear la cuenta de otra persona? Sal de esta cuenta y llena el formulario. | H33: Pendiente | K33: Persona solicitante | L33: Página (sitio/cuenta.html)
A34: T033 | B34: Crea tu cuenta | C34: — | D34: Texto | E34: Si hay un borrador guardado en el navegador | F34: Tienes una cuenta sin crear guardada en este dispositivo, con lo que habías escrito. La contraseña y la fotografía no se guardan: tendrás que ponerlas otra vez. | H34: Pendiente | K34: Persona solicitante | L34: Página (sitio/cuenta.html)
A35: T034 | B35: Crea tu cuenta | C35: — | D35: Botón o enlace | E35: Si hay un borrador guardado en el navegador | F35: Recuperar lo que escribiste | H35: Pendiente | K35: Persona solicitante | L35: Página (sitio/cuenta.html)
A36: T035 | B36: Crea tu cuenta | C36: — | D36: Botón o enlace | E36: Si hay un borrador guardado en el navegador | F36: Empezar de nuevo | H36: Pendiente | K36: Persona solicitante | L36: Página (sitio/cuenta.html)
A37: T036 | B37: Crea tu cuenta | C37: — | D37: Aviso | E37: Si hay un borrador guardado en el navegador | F37: ¿Descartar lo que escribiste? Se borra de este dispositivo y no se puede deshacer. ConservarDescartar | H37: Pendiente | K37: Persona solicitante | L37: Página (sitio/cuenta.html)
A38: T037 | B38: Crea tu cuenta | C38: Quién eres · ¿Quién eres? | D38: Título | E38: Siempre | F38: ¿Quién eres? | H38: Pendiente | K38: Persona solicitante | L38: Página (sitio/cuenta.html)
... A139: T138 | B139: Crea tu cuenta | C139: Aviso de privacidad simplificado | D139: Texto | E139: Al abrir la ventana «Aviso de privacidad simplificado» | F139: La Secretaría del Medio Ambiente recaba tu nombre, CURP (y de ella tu sexo), fotografía de frente, correo, teléfono y la institución para la que trabajas, si es el caso, para crear tu cuenta, tramitar tu acreditación, reconocerte en la cita, el curso y el examen, avisarte el avance y llevar el padrón de personas acreditadas. Al entregarte la credencial te toma otra fotografía, que es la que se imprime en ella. | H139: Pendiente | K139: Persona solicitante | L139: Página (sitio/cuenta.html)
A140: T139 | B140: Crea tu cuenta | C140: Aviso de privacidad simplificado | D140: Texto | E140: Al abrir la ventana «Aviso de privacidad simplificado» | F140: Fundamento: [Art. __, fracc. __]. Pendiente: lo completa la Unidad de Transparencia. | H140: Pendiente | J140: Lo completa la Unidad de Transparencia; no se inventa la cita. | K140: Persona solicitante | L140: Página (sitio/cuenta.html)
A141: T140 | B141: Crea tu cuenta | C141: Aviso de privacidad simplificado | D141: Botón o enlace | E141: Al abrir la ventana «Aviso de privacidad simplificado» | F141: Cerrar | H141: Pendiente | K141: Persona solicitante | L141: Página (sitio/cuenta.html)
A142: T141 | B142: Crea tu cuenta | C142: Al crear la cuenta | D142: Error | E142: Si ya hay una cuenta con esa CURP | F142: Ya hay una cuenta con esta CURP. Entra con ella; si no recuerdas tu contraseña, pide ayuda a la Secretaría. | H142: Pendiente | K142: Persona solicitante | L142: Código del sitio (sitio/app/config-cuenta.js)
A143: T142 | B143: Crea tu cuenta | C143: Al crear la cuenta | D143: Error | E143: CURP del registro de Kobo con otro nombre | F143: Tu nombre no coincide con el registro anterior de la Secretaría para esta CURP. Acude a la Secretaría para aclararlo. | H143: Pendiente | K143: Persona solicitante | L143: Código del sitio (sitio/app/config-cuenta.js)
A144: T143 | B144: Crea tu cuenta | C144: CURP | D144: Error | E144: Si la CURP no corresponde al nombre y apellidos | F144: La CURP no corresponde con el nombre y los apellidos que escribiste. Escríbelos tal como aparecen en tu CURP. | H144: Pendiente | K144: Persona solicitante | L144: Estándar de formularios (cruzada curp-nombre, sitio/formkit/js/validaciones.config.js)
A145: T144 | B145: Crea tu cuenta | C145: CURP | D145: Error | E145: Si la CURP indica segundo apellido y no se escribió | F145: Tu CURP indica que tienes segundo apellido. Escríbelo tal como aparece en tu CURP. | H145: Pendiente | K145: Persona solicitante | L145: Estándar de formularios (cruzada curp-segundo-apellido, sitio/formkit/js/validaciones.config.js)
A146: T145 | B146: Entrar | C146: — | D146: Botón o enlace | E146: Siempre | F146: Inicio | H146: Pendiente | K146: Persona solicitante | L146: Página (sitio/entrar.html)
A147: T146 | B147: Entrar | C147: Entra a tu cuenta | D147: Título | E147: Siempre | F147: Entra a tu cuenta | H147: Pendiente | K147: Persona solicitante | L147: Página (sitio/entrar.html)
A148: T147 | B148: Entrar | C148: Entra a tu cuenta | D148: Nota | E148: Siempre | F148: Las preguntas con * son obligatorias. | H148: Pendiente | K148: Persona solicitante | L148: Página (sitio/entrar.html)
A149: T148 | B149: Entrar | C149: Entra a tu cuenta | D149: Pregunta | E149: Siempre | F149: CURP | H149: Pendiente | K149: Persona solicitante | L149: Página (sitio/entrar.html)
A150: T149 | B150: Entrar | C150: Entra a tu cuenta | D150: Pregunta | E150: Siempre | F150: Contraseña | H150: Pendiente | K150: Persona solicitante | L150: Página (sitio/entrar.html)
A151: T150 | B151: Entrar | C151: Entra a tu cuenta | D151: Botón o enlace | E151: Siempre | F151: Entrar | H151: Pendiente | K151: Persona solicitante | L151: Página (sitio/entrar.html)
A152: T151 | B152: Entrar | C152: Entra a tu cuenta | D152: Texto | E152: Siempre | F152: ¿No tienes cuenta? Créala aquí. | H152: Pendiente | K152: Persona solicitante | L152: Página (sitio/entrar.html)
A153: T152 | B153: Entrar | C153: Entra a tu cuenta | D153: Texto | E153: Siempre | F153: ¿Olvidaste tu contraseña? En el sistema definitivo recibirás en tu correo un enlace de un solo uso para crear otra. En esta versión de prueba no se envían correos. | H153: Pendiente | J153: Falta definir quién atiende la recuperación de contraseña (pendiente). | K153: Persona solicitante | L153: Página (sitio/entrar.html)
A154: T153 | B154: Entrar | C154: Entra a tu cuenta | D154: Texto | E154: Siempre | F154: Versión de prueba: todas las personas de ejemplo tienen la contraseña . Para escoger una, abre el «Menú de pruebas». | H154: Pendiente | K154: Persona solicitante | L154: Página (sitio/entrar.html)
A155: T154 | B155: Entrar | C155: Entra a tu cuenta | D155: Error | E155: CURP del registro de Kobo sin cuenta | F155: Esta CURP tiene acreditaciones anteriores, pero todavía no tiene cuenta. Crea tu cuenta con ella para verlas. | H155: Pendiente | K155: Persona solicitante | L155: Código del sitio (sitio/app/config-entrar.js)
A156: T155 | B156: Entrar | C156: Entra a tu cuenta | D156: Error | E156: CURP o contraseña incorrectas | F156: La CURP o la contraseña no coinciden. Revisa ambas e intenta de nuevo. | H156: Pendiente | K156: Persona solicitante | L156: Código del sitio (sitio/app/config-entrar.js)
A157: T156 | B157: Pantallas con cuenta | C157: Cabecera de sesión | D157: Botón o enlace | E157: Con sesión iniciada | F157: Mis trámites | H157: Pendiente | K157: Persona solicitante | L157: Código del sitio (sitio/app/apd.js)
A158: T157 | B158: Pantallas con cuenta | C158: Cabecera de sesión | D158: Botón o enlace | E158: Con sesión iniciada | F158: Mis datos | H158: Pendiente | K158: Persona solicitante | L158: Código del sitio (sitio/app/apd.js)
A159: T158 | B159: Pantallas con cuenta | C159: Cabecera de sesión | D159: Botón o enlace | E159: Con sesión iniciada | F159: Salir | H159: Pendiente | K159: Persona solicitante | L159: Código del sitio (sitio/app/apd.js)
A160: T159 | B160: Mis trámites | C160: Mis trámites | D160: Título | E160: Siempre | F160: Mis trámites | H160: Pendiente | K160: Persona solicitante | L160: Página (sitio/tramites.html)
A161: T160 | B161: Mis trámites | C161: Mis trámites | D161: Introducción | E161: Siempre | F161: Cargando tu información… | H161: Pendiente | J161: Texto momentáneo mientras cargan los datos. | K161: Persona solicitante | L161: Página (sitio/tramites.html)
A162: T161 | B162: Mis trámites | C162: Mis trámites | D162: Botón o enlace | E162: Al crear la cuenta con éxito | F162: Iniciar una solicitud | H162: Pendiente | K162: Persona solicitante | L162: Página (sitio/tramites.html)
A163: T162 | B163: Mis trámites | C163: Solicitudes en curso | D163: Subtítulo | E163: Siempre | F163: Solicitudes en curso | H163: Pendiente | K163: Persona solicitante | L163: Página (sitio/tramites.html)
A164: T163 | B164: Mis trámites | C164: Dónde es | D164: Subtítulo | E164: Siempre | F164: Dónde es | H164: Pendiente | K164: Persona solicitante | L164: Página (sitio/tramites.html)
A165: T164 | B165: Mis trámites | C165: Mis acreditaciones | D165: Subtítulo | E165: Siempre | F165: Mis acreditaciones | H165: Pendiente | K165: Persona solicitante | L165: Página (sitio/tramites.html)
A166: T165 | B166: Mis trámites | C166: Solicitudes anteriores | D166: Subtítulo | E166: Siempre | F166: Solicitudes anteriores | H166: Pendiente | K166: Persona solicitante | L166: Página (sitio/tramites.html)
A167: T166 | B167: Mis trámites | C167: Mis solicitudes · estado | D167: Estado | E167: Solicitud en borrador | F167: Borrador | H167: Pendiente | K167: Persona solicitante | L167: Código del sitio (sitio/app/apd.js)
A168: T167 | B168: Mis trámites | C168: Mis solicitudes · qué sigue | D168: Texto | E168: Solicitud en borrador | F168: Termina de cargar tus documentos y envía tu solicitud. | H168: Pendiente | K168: Persona solicitante | L168: Código del sitio (sitio/app/apd.js)
A169: T168 | B169: Mis trámites | C169: Mis solicitudes · estado | D169: Estado | E169: Solicitud enviada | F169: En revisión documental | H169: Pendiente | K169: Persona solicitante | L169: Código del sitio (sitio/app/apd.js)
A170: T169 | B170: Mis trámites | C170: Mis solicitudes · qué sigue | D170: Texto | E170: Solicitud enviada | F170: La Secretaría hace la revisión documental de tu solicitud: revisa que tus documentos estén completos y correctos. | H170: Pendiente | K170: Persona solicitante | L170: Código del sitio (sitio/app/apd.js)
A171: T170 | B171: Mis trámites | C171: Mis solicitudes · estado | D171: Estado | E171: Solicitud con observaciones | F171: Con observaciones | H171: Pendiente | K171: Persona solicitante | L171: Código del sitio (sitio/app/apd.js)
A172: T171 | B172: Mis trámites | C172: Mis solicitudes · qué sigue | D172: Texto | E172: Solicitud con observaciones | F172: Corrige lo que se indica abajo y vuelve a enviar tu solicitud. | H172: Pendiente | K172: Persona solicitante | L172: Código del sitio (sitio/app/apd.js)
A173: T172 | B173: Mis trámites | C173: Mis solicitudes · estado | D173: Estado | E173: Solicitud validada en línea (con cita) | F173: Cita asignada | H173: Pendiente | K173: Persona solicitante | L173: Código del sitio (sitio/app/apd.js)
... A351: T350 | B351: Solicitud | C351: Aviso de privacidad simplificado | D351: Texto | E351: Al abrir la ventana «Aviso de privacidad simplificado» | F351: La verificación pública de acreditaciones muestra sólo tu nombre, el tipo y número de acreditación y su vigencia. | H351: Pendiente | K351: Persona solicitante | L351: Página (sitio/solicitud.html)
A352: T351 | B352: Solicitud | C352: Aviso de privacidad simplificado | D352: Texto | E352: Al abrir la ventana «Aviso de privacidad simplificado» | F352: Fundamento: [Art. __, fracc. __]. Pendiente: lo completa la Unidad de Transparencia. | H352: Pendiente | J352: Lo completa la Unidad de Transparencia; no se inventa la cita. | K352: Persona solicitante | L352: Página (sitio/solicitud.html)
A353: T352 | B353: Solicitud | C353: Aviso de privacidad simplificado | D353: Botón o enlace | E353: Al abrir la ventana «Aviso de privacidad simplificado» | F353: Cerrar | H353: Pendiente | K353: Persona solicitante | L353: Página (sitio/solicitud.html)
A354: T353 | B354: Solicitud | C354: Trámite · acreditación deshabilitada | D354: Motivo | E354: Ya tiene un trámite de ese tipo en curso | F354: Ya tienes un trámite en curso (folio APD-S-…). | H354: Pendiente | K354: Persona solicitante | L354: Código del sitio (sitio/app/apd.js)
A355: T354 | B355: Solicitud | C355: Trámite · acreditación deshabilitada | D355: Motivo | E355: Vigente y todavía no renovable | F355: Tu acreditación PD-… vence el DD/MM/AAAA. Podrás renovarla a partir del DD/MM/AAAA. | H355: Pendiente | K355: Persona solicitante | L355: Código del sitio (sitio/app/apd.js)
A356: T355 | B356: Solicitud | C356: Trámite · acreditación deshabilitada | D356: Motivo | E356: Emitida con vigencia futura | F356: Tu acreditación PD-… todavía no entra en vigor. | H356: Pendiente | K356: Persona solicitante | L356: Código del sitio (sitio/app/apd.js)
A357: T356 | B357: Solicitud | C357: Trámite · acreditación deshabilitada | D357: Motivo | E357: Dictaminador sin poda vigente | F357: Necesitas tener vigente tu acreditación de poda y derribo. | H357: Pendiente | K357: Persona solicitante | L357: Código del sitio (sitio/app/apd.js)
A358: T357 | B358: Solicitud | C358: Trámite · modalidad | D358: Texto | E358: Le corresponde renovación | F358: Te corresponde la renovación de tu acreditación PD-…. Curso de N días. | H358: Pendiente | K358: Persona solicitante | L358: Código del sitio (sitio/app/solicitud.js)
A359: T358 | B359: Solicitud | C359: Trámite · modalidad | D359: Texto | E359: Le corresponde solicitud nueva | F359: Te corresponde una solicitud nueva: es tu primera vez o tu acreditación anterior venció hace más de un año. Curso de N días. | H359: Pendiente | K359: Persona solicitante | L359: Código del sitio (sitio/app/solicitud.js)
A360: T359 | B360: Solicitud | C360: Trámite · adscripción | D360: Valor | E360: Persona independiente | F360: Independiente: no trabajas para ninguna empresa, institución o dependencia. | H360: Pendiente | K360: Persona solicitante | L360: Código del sitio (sitio/app/apd.js)
A361: T360 | B361: Solicitud | C361: Trámite · adscripción | D361: Valor | E361: Persona con adscripción | F361: «Tipo»: «Nombre de la institución». (tipos: Empresa, consultoría o particular · Dependencia del Gobierno de la Ciudad de México · Alcaldía · Dependencia del Gobierno Federal · Institución educativa) | H361: Pendiente | K361: Persona solicitante | L361: Código del sitio (sitio/app/apd.js)
A362: T361 | B362: Solicitud | C362: Trámite · adscripción | D362: Valor | E362: Cuenta sin adscripción | F362: sin indicar. Antes de enviar, indica en «Mis datos» si trabajas para alguna empresa, institución o dependencia. | H362: Pendiente | K362: Persona solicitante | L362: Código del sitio (sitio/app/solicitud.js)
A363: T362 | B363: Solicitud | C363: Trámite · experiencia | D363: Ayuda (cambia) | E363: Dictaminador con perfil que pide 2 años | F363: Con tu perfil se piden al menos dos años. | H363: Pendiente | K363: Persona solicitante | L363: Código del sitio (sitio/app/solicitud.js)
A364: T363 | B364: Solicitud | C364: Trámite · experiencia | D364: Ayuda (cambia) | E364: Dictaminador con perfil que pide 5 años o que podría no cumplir | F364: Con tu perfil se piden al menos cinco años. | H364: Pendiente | K364: Persona solicitante | L364: Código del sitio (sitio/app/solicitud.js)
... A505: T504 | B505: Mensajes del formulario (estándar) | C505: Validación y envío | D505: Mensaje | E505: Mensaje «tablaDescendente» | F505: descendente | H505: Pendiente | K505: Persona solicitante | L505: Estándar de formularios (validaciones.config.js); se cambia en el estándar o se sobrescribe en el proyecto
A506: T505 | B506: Mensajes del formulario (estándar) | C506: Validación y envío | D506: Mensaje | E506: Mensaje «visorCargando» | F506: Cargando el documento… | H506: Pendiente | J506: Texto momentáneo mientras cargan los datos. | K506: Persona solicitante | L506: Estándar de formularios (validaciones.config.js); se cambia en el estándar o se sobrescribe en el proyecto
A507: T506 | B507: Mensajes del formulario (estándar) | C507: Validación y envío | D507: Mensaje | E507: Mensaje «visorError» | F507: No se pudo mostrar el documento aquí. Ábrelo en otra pestaña con el enlace de arriba. | H507: Pendiente | K507: Persona solicitante | L507: Estándar de formularios (validaciones.config.js); se cambia en el estándar o se sobrescribe en el proyecto
A508: T507 | B508: Mensajes del formulario (estándar) | C508: Validación y envío | D508: Mensaje | E508: Mensaje «visorNavegador» | F508: Se muestra con el visor del navegador. Si no lo ves completo, ábrelo en otra pestaña con el enlace de arriba. | H508: Pendiente | K508: Persona solicitante | L508: Estándar de formularios (validaciones.config.js); se cambia en el estándar o se sobrescribe en el proyecto
A509: T508 | B509: Mensajes del formulario (estándar) | C509: Validación y envío | D509: Mensaje | E509: Mensaje «visorHoja» | F509: Hoja {n} de {total} | H509: Pendiente | K509: Persona solicitante | L509: Estándar de formularios (validaciones.config.js); se cambia en el estándar o se sobrescribe en el proyecto
A510: T509 | B510: Mensajes del formulario (estándar) | C510: Validación y envío | D510: Mensaje | E510: Mensaje «archRechazoProceso» | F510: no se pudo procesar el archivo. Intenta de nuevo. | H510: Pendiente | K510: Persona solicitante | L510: Estándar de formularios (validaciones.config.js); se cambia en el estándar o se sobrescribe en el proyecto
A511: T510 | B511: Mensajes del formulario (estándar) | C511: Validación y envío | D511: Mensaje | E511: Mensaje «copiarBoton» | F511: Copiado | H511: Pendiente | K511: Persona solicitante | L511: Estándar de formularios (validaciones.config.js); se cambia en el estándar o se sobrescribe en el proyecto
A512: T511 | B512: Mensajes del formulario (estándar) | C512: Validación y envío | D512: Mensaje | E512: Mensaje «copiarBotonFallo» | F512: No se pudo copiar | H512: Pendiente | K512: Persona solicitante | L512: Estándar de formularios (validaciones.config.js); se cambia en el estándar o se sobrescribe en el proyecto
A513: T512 | B513: Mensajes del formulario (estándar) | C513: Validación y envío | D513: Mensaje | E513: Mensaje «enlaceNuevaPestana» | F513: (se abre en otra pestaña) | H513: Pendiente | K513: Persona solicitante | L513: Estándar de formularios (validaciones.config.js); se cambia en el estándar o se sobrescribe en el proyecto
A514: T513 | B514: Mensajes del formulario (estándar) | C514: Validación y envío | D514: Mensaje | E514: Mensaje «descargaBoton» | F514: Preparando… | H514: Pendiente | K514: Persona solicitante | L514: Estándar de formularios (validaciones.config.js); se cambia en el estándar o se sobrescribe en el proyecto
A515: T514 | B515: Mensajes del formulario (estándar) | C515: Validación y envío | D515: Mensaje | E515: Mensaje «conjuncion» | F515: y | H515: Pendiente | K515: Persona solicitante | L515: Estándar de formularios (validaciones.config.js); se cambia en el estándar o se sobrescribe en el proyecto
A516: T515 | B516: Mensajes del formulario (estándar) | C516: Validación y envío | D516: Mensaje | E516: Mensaje «fechaAtajos» | F516: Atajos de periodo | H516: Pendiente | K516: Persona solicitante | L516: Estándar de formularios (validaciones.config.js); se cambia en el estándar o se sobrescribe en el proyecto
A517: T516 | B517: Mensajes del formulario (estándar) | C517: Validación y envío | D517: Mensaje | E517: Mensaje «fechaUltimos» | F517: Últimos {n} días | H517: Pendiente | K517: Persona solicitante | L517: Estándar de formularios (validaciones.config.js); se cambia en el estándar o se sobrescribe en el proyecto
A518: T517 | B518: Mensajes del formulario (estándar) | C518: Validación y envío | D518: Mensaje | E518: Mensaje «fechaPeriodo» | F518: Periodo: del {desde} al {hasta} | H518: Pendiente | K518: Persona solicitante | L518: Estándar de formularios (validaciones.config.js); se cambia en el estándar o se sobrescribe en el proyecto
... A522: T521 | B522: Mensajes del formulario (estándar) | C522: Validación y envío | D522: Mensaje | E522: Mensaje «sexoX» | F522: No binario | H522: Pendiente | K522: Persona solicitante | L522: Estándar de formularios (validaciones.config.js); se cambia en el estándar o se sobrescribe en el proyecto
A523: T522 | B523: Mensajes del formulario (estándar) | C523: Validación y envío | D523: Mensaje | E523: Mensaje «cargando» | F523: Cargando… | H523: Pendiente | J523: Texto momentáneo mientras cargan los datos. | K523: Persona solicitante | L523: Estándar de formularios (validaciones.config.js); se cambia en el estándar o se sobrescribe en el proyecto
A524: T523 | B524: Mensajes del formulario (estándar) | C524: Validación y envío | D524: Mensaje | E524: Mensaje «pestanaAnuncio» | F524: Pestaña {nombre} | H524: Pendiente | K524: Persona solicitante | L524: Estándar de formularios (validaciones.config.js); se cambia en el estándar o se sobrescribe en el proyecto
A525: T524 | B525: Mensajes del formulario (estándar) | C525: Validación y envío | D525: Mensaje | E525: Mensaje «compartido» | F525: Compartido. | H525: Pendiente | K525: Persona solicitante | L525: Estándar de formularios (validaciones.config.js); se cambia en el estándar o se sobrescribe en el proyecto
A526: T525 | B526: Mensajes del formulario (estándar) | C526: Validación y envío | D526: Mensaje | E526: Mensaje «borradorRecuperado» | F526: Borrador recuperado en este dispositivo. | H526: Pendiente | K526: Persona solicitante | L526: Estándar de formularios (validaciones.config.js); se cambia en el estándar o se sobrescribe en el proyecto
A527: T526 | B527: Mensajes al guardar o enviar | C527: Reglas de la base | D527: Error | E527: Regla «bitacora_directa» | F527: La bitácora sólo la escriben las reglas de la base | H527: Pendiente | K527: Personal de la Secretaría | L527: Base de datos (db/apd/03-apd-reglas.sql)
A528: T527 | B528: Mensajes al guardar o enviar | C528: Reglas de la base | D528: Error | E528: Regla «monto_de_personal» | F528: El costo del curso lo actualiza el personal de la Secretaría | H528: Pendiente | K528: Personal de la Secretaría | L528: Base de datos (db/apd/03-apd-reglas.sql)
A529: T528 | B529: Mensajes al guardar o enviar | C529: Reglas de la base | D529: Error | E529: Regla «cuota_de_personal» | F529: La cuota la actualiza el personal de la Secretaría | H529: Pendiente | K529: Personal de la Secretaría | L529: Base de datos (db/apd/03-apd-reglas.sql)
A530: T529 | B530: Mensajes al guardar o enviar | C530: Reglas de la base | D530: Error | E530: Regla «organizacion_sin_nombre» | F530: La organización necesita un nombre | H530: Pendiente | K530: Personal de la Secretaría | L530: Base de datos (db/apd/03-apd-reglas.sql)
A531: T530 | B531: Mensajes al guardar o enviar | C531: Reglas de la base | D531: Error | E531: Regla «carrera_sin_nombre» | F531: La carrera necesita un nombre | H531: Pendiente | K531: Personal de la Secretaría | L531: Base de datos (db/apd/03-apd-reglas.sql)
...
